{
  "parent": "minecraft:end/root",
  "display": {
    "icon": {
      "item": "minecraft:dragon_head"
    },
    "title": {
      "translate": "advancements.end.ride_dragon.title"
    },
    "description": {
      "translate": "advancements.end.ride_dragon.description"
    },
    "frame": "task",
    "show_toast": true,
    "announce_to_chat": true,
    "hidden": false
  },
  "criteria": {
    "ride_dragon": {
      "trigger": "minecraft:started_riding",
      "conditions": {
        "player": [
          {
            "condition": "minecraft:entity_properties",
            "predicate": {
              "vehicle": {
                "type": "minecraft:ender_dragon"
              }
            },
            "entity": "this"
          }
        ]
      }
    }
  },
  "requirements": [
    [
      "ride_dragon"
    ]
  ]
}